datalicious/__init__.py
datalicious/flex/__init__.py
datalicious/flex/tags.py
datalicious-2024.8.0.dist-info/WHEEL
datalicious-2024.8.0.dist-info/METADATA
datalicious-2024.8.0.dist-info/RECORD
