Metadata-Version: 2.1
Name: datalicious
Version: 2024.8.0
Summary: delicious native market data
Author-email: Eugene Van den Bulke <eugene.vandenbulke@gmail.com>
Project-URL: Home, http://github.com/3kwa/datalicious
